createmypypackage/__init__.py
createmypypackage/__main__.py
createmypypackage-1.0.4.dist-info/LICENSE
createmypypackage-1.0.4.dist-info/METADATA
createmypypackage-1.0.4.dist-info/WHEEL
createmypypackage-1.0.4.dist-info/entry_points.txt
createmypypackage-1.0.4.dist-info/top_level.txt
createmypypackage-1.0.4.dist-info/RECORD
