Metadata-Version: 2.1
Name: createmypypackage
Version: 1.0.4
Summary: One command simplest way to make and upload a python package!
Home-page: https://github.com/Souvic/createmypypackage.git
Author: Souvic Chakraborty
Author-email: chakra.souvic@gmail.com
License: UNKNOWN
Project-URL: Bug Tracker, https://github.com/Souvic/createmypypackage.git/issues
Platform: UNKNOWN
Classifier: Programming Language :: Python :: 3
Classifier: License :: OSI Approved :: MIT License
Classifier: Operating System :: OS Independent
Requires-Python: >=3.6
License-File: LICENSE
Requires-Dist: build (>=0.5)
Requires-Dist: virtualenv (>=20.4.7)
Requires-Dist: pipreqs (>=0.4.10)
Requires-Dist: twine (>=3.4.1)
